bilibili_video_info_mcp/__init__.py
bilibili_video_info_mcp/__main__.py
bilibili_video_info_mcp/bilibili_api.py
bilibili_video_info_mcp/server.py
bilibili_video_info_mcp-0.2.0.dist-info/licenses/LICENSE
bilibili_video_info_mcp-0.2.0.dist-info/METADATA
bilibili_video_info_mcp-0.2.0.dist-info/WHEEL
bilibili_video_info_mcp-0.2.0.dist-info/entry_points.txt
bilibili_video_info_mcp-0.2.0.dist-info/top_level.txt
bilibili_video_info_mcp-0.2.0.dist-info/RECORD
